Metadata-Version: 2.4
Name: quantsapp-dev
Version: 0.0.1.dev3
Summary: Quantsapp
Project-URL: Homepage, https://github.com/pypa/sampleproject
Project-URL: Issues, https://github.com/pypa/sampleproject/issues
Author-email: Quantsapp <support@quantsapp.com>
License-Expression: MIT
License-File: LICENSE
Classifier: Operating System :: OS Independent
Classifier: Programming Language :: Python :: 3
Classifier: Programming Language :: Python :: 3.11
Classifier: Programming Language :: Python :: 3.12
Classifier: Programming Language :: Python :: 3.13
Requires-Python: >=3.11
Requires-Dist: pydantic~=2.11.4
Requires-Dist: requests~=2.32.3
Requires-Dist: websocket-client~=1.8.0
